pj_logging/__init__.py
pj_logging/pj_logging.py
pj_logging/py.typed
pj_logging-0.1.5.dist-info/LICENSE
pj_logging-0.1.5.dist-info/METADATA
pj_logging-0.1.5.dist-info/WHEEL
pj_logging-0.1.5.dist-info/top_level.txt
pj_logging-0.1.5.dist-info/RECORD
