Metadata-Version: 2.2
Name: pj_logging
Version: 0.1.5
Summary: Panel rich and jsonl logging.
Author: the-citto
License: Copyright (c) 2025 the-citto
Project-URL: Repository, https://github.com/the-citto/pj-logging
Classifier: License :: OSI Approved :: MIT License
Classifier: Operating System :: POSIX :: Linux
Classifier: Programming Language :: Python
Classifier: Programming Language :: Python :: 3
Classifier: Typing :: Typed
Requires-Python: >=3.11
License-File: LICENSE
Requires-Dist: rich>=13.9
Provides-Extra: tests
Requires-Dist: pj_logging; extra == "tests"
Requires-Dist: coverage; extra == "tests"
Requires-Dist: pytest; extra == "tests"
Requires-Dist: pytest-cov; extra == "tests"
Requires-Dist: pytest-mypy; extra == "tests"
Requires-Dist: pytest-ruff; extra == "tests"
Requires-Dist: pytest-pyright; extra == "tests"
Provides-Extra: dev
Requires-Dist: pj_logging[tests]; extra == "dev"
Requires-Dist: ipython; extra == "dev"
